xhs_auto_down/__init__.py
xhs_auto_down/CLI/__init__.py
xhs_auto_down/CLI/main.py
xhs_auto_down/TUI/__init__.py
xhs_auto_down/TUI/about.py
xhs_auto_down/TUI/app.py
xhs_auto_down/TUI/index.py
xhs_auto_down/TUI/loading.py
xhs_auto_down/TUI/monitor.py
xhs_auto_down/TUI/progress.py
xhs_auto_down/TUI/record.py
xhs_auto_down/TUI/setting.py
xhs_auto_down/TUI/update.py
xhs_auto_down/application/__init__.py
xhs_auto_down/application/app.py
xhs_auto_down/application/download.py
xhs_auto_down/application/explore.py
xhs_auto_down/application/image.py
xhs_auto_down/application/request.py
xhs_auto_down/application/video.py
xhs_auto_down/expansion/__init__.py
xhs_auto_down/expansion/browser.py
xhs_auto_down/expansion/cleaner.py
xhs_auto_down/expansion/converter.py
xhs_auto_down/expansion/file_folder.py
xhs_auto_down/expansion/namespace.py
xhs_auto_down/expansion/truncate.py
xhs_auto_down/module/__init__.py
xhs_auto_down/module/extend.py
xhs_auto_down/module/manager.py
xhs_auto_down/module/model.py
xhs_auto_down/module/recorder.py
xhs_auto_down/module/settings.py
xhs_auto_down/module/static.py
xhs_auto_down/module/tools.py
xhs_auto_down/module/translator.py
xhs_auto_down-0.2.0.dist-info/LICENSE
xhs_auto_down-0.2.0.dist-info/METADATA
xhs_auto_down-0.2.0.dist-info/WHEEL
xhs_auto_down-0.2.0.dist-info/top_level.txt
xhs_auto_down-0.2.0.dist-info/RECORD
