Metadata-Version: 2.1
Name: xhs_auto_down
Version: 0.2.0
Summary: A brief description of your package
Home-page: https://github.com/yourusername/your_package_name
Author: bauyin
Author-email: your_email@example.com
Classifier: Programming Language :: Python :: 3
Classifier: License :: OSI Approved :: MIT License
Classifier: Operating System :: OS Independent
Requires-Python: >=3.12
License-File: LICENSE
Requires-Dist: textual <=0.63.0
Requires-Dist: pyperclip >=1.9.0
Requires-Dist: lxml >=5.3.0
Requires-Dist: PyYAML >=6.0.2
Requires-Dist: aiosqlite >=0.20.0
Requires-Dist: click >=8.1.7
Requires-Dist: rookiepy >=0.5.2
Requires-Dist: httpx >=0.27.0
Requires-Dist: fastapi >=0.112.1
Requires-Dist: uvicorn >=0.30.6
Requires-Dist: aiofiles >=24.1.0
Requires-Dist: emoji >=2.12.1
